amazon_product_search/__init__.py
amazon_product_search/amazon_product_search.py
amazon_product_search_v2-0.1.1.dist-info/LICENSE
amazon_product_search_v2-0.1.1.dist-info/METADATA
amazon_product_search_v2-0.1.1.dist-info/WHEEL
amazon_product_search_v2-0.1.1.dist-info/top_level.txt
amazon_product_search_v2-0.1.1.dist-info/RECORD
