Metadata-Version: 2.2
Name: amazon_product_search_v2
Version: 0.1.1
Summary: A library to search products on Amazon without using the PA API
Home-page: https://github.com/ManojPanda3/amazon-product-search
Author: Manojpanda
Author-email: Manojpanda <manojpandawork@gmail.com>
License: Copyright (c) 2025 Manoj Panda
Project-URL: Homepage, https://github.com/ManojPanda3/amazon-product-search
Keywords: amazon,product,search,scraping,web scraping
Classifier: Development Status :: 3 - Alpha
Classifier: Intended Audience :: Developers
Classifier: License :: OSI Approved :: MIT License
Classifier: Programming Language :: Python :: 3
Classifier: Programming Language :: Python :: 3.7
Classifier: Programming Language :: Python :: 3.8
Classifier: Programming Language :: Python :: 3.9
Classifier: Programming Language :: Python :: 3.10
Classifier: Programming Language :: Python :: 3.11
Classifier: Programming Language :: Python :: 3.12
Classifier: Programming Language :: Python :: 3.13
Classifier: Topic :: Software Development :: Libraries :: Python Modules
Requires-Python: >=3.7
License-File: LICENSE
Requires-Dist: beautifulsoup4==4.12.3
Requires-Dist: requests==2.32.3
Requires-Dist: lxml==5.3.1
Dynamic: author
Dynamic: home-page
Dynamic: requires-python
